patentdata/__init__.py
patentdata/datacache.py
patentdata/datamodels.py
patentdata/patentqueries.py
patentdata/utils.py
patentdata/xmlparser.py
patentdata/corpus/__init__.py
patentdata/corpus/baseclasses.py
patentdata/corpus/epo/__init__.py
patentdata/corpus/epo/ops.py
patentdata/corpus/epo/settings.py
patentdata/corpus/uspto/__init__.py
patentdata/corpus/uspto/grants.py
patentdata/corpus/uspto/publications.py
patentdata/models/__init__.py
patentdata/models/basemodels.py
patentdata/models/claim.py
patentdata/models/claimset.py
patentdata/models/classification.py
patentdata/models/patentcorpus.py
patentdata/models/specification.py
patentdata/models/lib/__init__.py
patentdata/models/lib/utils.py
patentdata/models/lib/utils_claim.py
patentdata/models/lib/utils_claimset.py
patentdata-0.0.7.dist-info/DESCRIPTION.rst
patentdata-0.0.7.dist-info/METADATA
patentdata-0.0.7.dist-info/RECORD
patentdata-0.0.7.dist-info/WHEEL
patentdata-0.0.7.dist-info/metadata.json
patentdata-0.0.7.dist-info/top_level.txt
