Metadata-Version: 2.0
Name: patentdata
Version: 0.0.7
Summary: A bag of functions and datamodels for playing around with patent data.
Home-page: https://github.com/benhoyle/patentdata
Author: Ben Hoyle
Author-email: benjhoyle@gmail.com
License: License
Requires-Dist: beautifulsoup4 (>=4.5.3)
Requires-Dist: lxml (>=3.7.3)
Requires-Dist: nltk (>=3.2.2)
Requires-Dist: pytest (>=3.0.6)
Requires-Dist: python-dateutil (>=2.6.0)
Requires-Dist: python-epo-ops-client (>=2.1.0)
Requires-Dist: requests (>=2.13.0)
Requires-Dist: six (>=1.10.0)
